radarr_sonarr_mcp/__init__.py
radarr_sonarr_mcp/cli.py
radarr_sonarr_mcp/server.py
radarr_sonarr_mcp/services/__init__.py
radarr_sonarr_mcp/services/jellyfin_service.py
radarr_sonarr_mcp/services/plex_service.py
radarr_sonarr_mcp/services/radarr_service.py
radarr_sonarr_mcp/services/sonarr_service.py
tests/__init__.py
tests/test_server.py
mseep_radarr_sonarr_mcp-0.1.2.dist-info/METADATA
mseep_radarr_sonarr_mcp-0.1.2.dist-info/WHEEL
mseep_radarr_sonarr_mcp-0.1.2.dist-info/entry_points.txt
mseep_radarr_sonarr_mcp-0.1.2.dist-info/top_level.txt
mseep_radarr_sonarr_mcp-0.1.2.dist-info/RECORD
