Metadata-Version: 2.4
Name: mseep-radarr-sonarr-mcp
Version: 0.1.2
Summary: MCP Server for Radarr and Sonarr media management
Home-page: 
Author: mseep
Author-email: mseep <support@skydeck.ai>
Maintainer: mseep
Maintainer-email: mseep <support@skydeck.ai>
Classifier: Programming Language :: Python :: 3
Classifier: License :: OSI Approved :: MIT License
Classifier: Operating System :: OS Independent
Requires-Python: >=3.7
Requires-Dist: mcp>=0.1.0
Requires-Dist: requests>=2.28.0
Requires-Dist: pydantic>=2.0.0
Provides-Extra: dev
Requires-Dist: pytest>=7.0.0; extra == "dev"
Dynamic: author
Dynamic: maintainer
Dynamic: requires-python
